MANIFEST.in
README.md
setup.cfg
setup.py
versioneer.py
pyipn/__init__.py
pyipn/_version.py
pyipn/detector.py
pyipn/effective_area.py
pyipn/fit.py
pyipn/geometry.py
pyipn/grb.py
pyipn/lightcurve.py
pyipn/numba_array.py
pyipn/possion_gen.py
pyipn/ppc.py
pyipn/rff.py
pyipn/universe.py
pyipn.egg-info/PKG-INFO
pyipn.egg-info/SOURCES.txt
pyipn.egg-info/dependency_links.txt
pyipn.egg-info/requires.txt
pyipn.egg-info/top_level.txt
pyipn/io/__init__.py
pyipn/io/package_utils.py
pyipn/io/plotting/__init__.py
pyipn/io/plotting/angle.py
pyipn/io/plotting/markers.py
pyipn/io/plotting/projection.py
pyipn/io/plotting/spherical_circle.py
pyipn/stan_models/__init__.py
pyipn/stan_models/model_builder.py
pyipn/stan_models/stan_builder.py
pyipn/stan_models/stan_models.py
pyipn/test/__init__.py
pyipn/test/conftest.py
pyipn/test/test_basic.py
pyipn/test/test_pyipn.py
pyipn/test/test_satellite_group.py
pyipn/utils/__init__.py
pyipn/utils/hdf5_utils.py
pyipn/utils/statistics.py
pyipn/utils/timing.py