Metadata-Version: 2.1
Name: pyipn
Version: 0.1.1
Summary: A population synthesis code for testing
Home-page: https://github.com/grburgessp/pyipn
Author: J. Michael Burgess
Author-email: jmichaelburgess@gmail.com
License: GPL-2+
Project-URL: Bug Tracker, https://github.com/grburgessp/pyipn/issues
Project-URL: Source Code, https://github.com/grburgessp/pyipn
Platform: UNKNOWN
Classifier: Development Status :: 2 - Pre-Alpha
Classifier: Environment :: Console
Classifier: Intended Audience :: Science/Research
Classifier: License :: OSI Approved :: GNU General Public License v2 or later (GPLv2+)
Classifier: Operating System :: POSIX
Classifier: Programming Language :: Python :: 3.5
Classifier: Programming Language :: Python :: 3.6
Classifier: Programming Language :: Python :: 3.7
Classifier: Programming Language :: Python :: 3.8
Classifier: Topic :: Scientific/Engineering :: Physics
